qigeometry/__init__.py
qigeometry/win/lib/geometry_module.dll
qigeometry/win/share/qi/module/geometry_module.mod
qigeometry-1.8.3.dist-info/LICENSE.txt
qigeometry-1.8.3.dist-info/METADATA
qigeometry-1.8.3.dist-info/WHEEL
qigeometry-1.8.3.dist-info/top_level.txt
qigeometry-1.8.3.dist-info/RECORD
